Workbook

Sheet Dashboard
B2: АНАЛИЗ АССОРТИМЕНТА И ПРОДАЖ NORTHWIND
B4: УНИКАЛЬНЫХ КАТЕГОРИЙ | D4: УНИКАЛЬНЫХ ТОВАРОВ | F4: ТОВАРОВ ПРОДАНО | H4: САМЫЙ ПРИБЫЛЬНЫЙ ТОВАР | J4: САМЫЙ ПРОДАВАЕМЫЙ ТОВАР | L4: САМЫЙ ДОРОГОЙ ТОВАР
B5: =_8_products_KPI[categories_unique] -> 16 | D5: =_8_products_KPI[products_unique] -> 45 | F5: =_8_products_KPI[products_sold] -> 2382 | H5: ='9_top_products'!B3 -> Northwind Traders Coffee | J5: ='9_top_products'!B2 -> Northwind Traders Beer | L5: ='9_top_products'!B4 -> Northwind Traders Marmalade
H7: ABC-АНАЛИЗ

Sheet Report
C2: НАБЛЮДЕНИЯ
B4: 1. | C4: Beverages - лидер среди категорий. Она существенно превосходит остальные по объему выручки и является ключевой для бизнеса. | D4: Подробнее
B5: 2. | C5: ABC-анализ демонстрирует узкий круг успешных товаров. Всего 9 товаров формируют около 80% выручки, что указывает на сильную зависимость выручки от ограниченного набора позиций. | D5: Подробнее
B6: 3. | C6: Выручка концентрируется у трех товаров. Распределение выручки крайне неравномерное - один товар, Northwind Traders Coffee, заметно опережает остальные, а большая доля выручки приходится на три ключевых товара: лидера по стоимости, лидера по продажам и лидера по выручке. | D6: Подробнее
B7: 4. | C7: Не все товары продаются. Значительная доля ассортимента приносит мало или вовсе не приносит дохода. Только 23 из 45 товаров дали выручку. | D7: Подробнее
B8: 5. | C8: Асимметрия цен. 60% товаров стоят дешевле среднего - в категориях могут быть единичные, но дорогие товары. Средняя цена категории может быть искажена несколькими дорогими товарами. | D8: Подробнее
B9: 6. | C9: Низкое товарное разнообразие внутри категорий. На каждую категорию приходится от 1 до 7 товаров, что также отражается на распределении относительно медианы. | D9: Подробнее
B10: 7. | C10: Хорошие продажи не тождественны большой прибыли. Northwind Traders Beer является самым продаваемым товаром, но не самым прибыльным. | D10: Подробнее
B11: 8. | C11: Высокая цена не гарантирует высокий вклад в доход. Northwind Traders Marmalade - самый дорогой товар, но не является самым прибыльным и по выручке лишь немного отличается от ряда более дешевых товаров. | D11: Подробнее
C12: ПРЕДЛОЖЕНИЯ
B13: 1. | C13: Пересмотреть ассортимент с низкой отдачей, особенно товары категории C по выручке и не давшие выручку.
B14: 2. | C14: Рассмотреть запуск промо для товаров, которые пока не принесли выручки.
B15: 3. | C15: Сфокусировать внимание на ключевых товарах и категории Beverages как на основном источнике дохода.
B16: 4. | C16: Использовать ABC-анализ и выручку в качестве базовых критериев при оценке ассортимента.
B17: 5. | C17: Проанализировать динамику продаж во времени.

Sheet 6_revenue_percent
A1: category | B1: id | C1: product_name | D1: revenue | E1: category_revenue | F1: share_percent | G1: category | H1: revenue_rating
A2: Baked Goods & Mixes | B2: 19 | C2: Northwind Traders Chocolate Biscuits Mix | D2: 690 | E2: 890 | F2: 0.775 | G2: Beverages | H2: 22636
A3: Baked Goods & Mixes | B3: 21 | C3: Northwind Traders Scones | D3: 200 | E3: 890 | F3: 0.225 | G3: Jams, Preserves | H3: 5490
A4: Beverages | B4: 43 | C4: Northwind Traders Coffee | D4: 14950 | E4: 22636 | F4: 0.66 | G4: Dried Fruit & Nuts | H4: 3660
A5: Beverages | B5: 34 | C5: Northwind Traders Beer | D5: 6818 | E5: 22636 | F5: 0.301 | G5: Dairy products | H5: 3132
A6: Beverages | B6: 81 | C6: Northwind Traders Green Tea | D6: 598 | E6: 22636 | F6: 0.026 | G6: Soups | H6: 2798.5
A7: Beverages | B7: 1 | C7: Northwind Traders Chai | D7: 270 | E7: 22636 | F7: 0.012 | G7: Candy | H7: 2550
A8: Candy | B8: 48 | C8: Northwind Traders Chocolate | D8: 2550 | E8: 2550 | F8: 1 | G8: Pasta | H8: 1950
A9: Canned Fruit & Vegetables | B9: 17 | C9: Northwind Traders Fruit Cocktail | D9: 1560 | E9: 1560 | F9: 1 | G9: Sauces | H9: 1800
A10: Canned Meat | B10: 40 | C10: Northwind Traders Crab Meat | D10: 1472 | E10: 1472 | F10: 1 | G10: Canned Fruit & Vegetables | H10: 1560
A11: Condiments | B11: 4 | C11: Northwind Traders Cajun Seasoning | D11: 660 | E11: 1160 | F11: 0.569 | G11: Canned Meat | H11: 1472
A12: Condiments | B12: 3 | C12: Northwind Traders Syrup | D12: 500 | E12: 1160 | F12: 0.431 | G12: Condiments | H12: 1160
A13: Dairy products | B13: 72 | C13: Northwind Traders Mozzarella | D13: 3132 | E13: 3132 | F13: 1 | G13: Baked Goods & Mixes | H13: 890
... A16: Dried Fruit & Nuts | B16: 74 | C16: Northwind Traders Almonds | D16: 200 | E16: 3660 | F16: 0.055 | G16: Общий итог | H16: 49912.25
A17: Dried Fruit & Nuts | B17: 80 | C17: Northwind Traders Dried Plums | D17: 140 | E17: 3660 | F17: 0.038
A18: Grains | B18: 52 | C18: Northwind Traders Long Grain Rice | D18: 280 | E18: 280 | F18: 1
A19: Jams, Preserves | B19: 20 | C19: Northwind Traders Marmalade | D19: 3240 | E19: 5490 | F19: 0.59
A20: Jams, Preserves | B20: 6 | C20: Northwind Traders Boysenberry Spread | D20: 2250 | E20: 5490 | F20: 0.41
A21: Oil | B21: 5 | C21: Northwind Traders Olive Oil | D21: 533.75 | E21: 533.75 | F21: 1
A22: Pasta | B22: 57 | C22: Northwind Traders Ravioli | D22: 1950 | E22: 1950 | F22: 1
A23: Pasta | B23: 56 | C23: Northwind Traders Gnocchi | D23: 0 | E23: 1950 | F23: 0
A24: Sauces | B24: 8 | C24: Northwind Traders Curry Sauce | D24: 1800 | E24: 1800 | F24: 1
A25: Soups | B25: 41 | C25: Northwind Traders Clam Chowder | D25: 2798.5 | E25: 2798.5 | F25: 1

Sheet 7_AVG_MED
A1: category | B1: product_name | C1: list_price | D1: average_price_comparison | E1: average_price | F1: median_price_comparison | G1: median_price
A2: Baked Goods & Mixes | B2: Northwind Traders Brownie Mix | C2: 12.49 | D2: > AVG | E2: 11.92 | F2: > MED | G2: 11.245
A3: Baked Goods & Mixes | B3: Northwind Traders Cake Mix | C3: 15.99 | D3: > AVG | E3: 11.92 | F3: > MED | G3: 11.245
A4: Baked Goods & Mixes | B4: Northwind Traders Chocolate Biscuits Mix | C4: 9.2 | D4: < AVG | E4: 11.92 | F4: < MED | G4: 11.245
A5: Baked Goods & Mixes | B5: Northwind Traders Scones | C5: 10 | D5: < AVG | E5: 11.92 | F5: < MED | G5: 11.245
A6: Beverages | B6: Northwind Traders Beer | C6: 14 | D6: < AVG | E6: 16.998 | F6: = MED | G6: 14
A7: Beverages | B7: Northwind Traders Chai | C7: 18 | D7: > AVG | E7: 16.998 | F7: > MED | G7: 14
A8: Beverages | B8: Northwind Traders Coffee | C8: 46 | D8: > AVG | E8: 16.998 | F8: > MED | G8: 14
A9: Beverages | B9: Northwind Traders Green Tea | C9: 2.99 | D9: < AVG | E9: 16.998 | F9: < MED | G9: 14
A10: Beverages | B10: Northwind Traders Tea | C10: 4 | D10: < AVG | E10: 16.998 | F10: < MED | G10: 14
A11: Candy | B11: Northwind Traders Chocolate | C11: 12.75 | D11: = AVG | E11: 12.75 | F11: = MED | G11: 12.75
A12: Canned Fruit & Vegetables | B12: Northwind Traders Cherry Pie Filling | C12: 2 | D12: < AVG | E12: 6.1875 | F12: > MED | G12: 1.5
A13: Canned Fruit & Vegetables | B13: Northwind Traders Corn | C13: 1.2 | D13: < AVG | E13: 6.1875 | F13: < MED | G13: 1.5
... A46: Soups | B46: Northwind Traders Vegetable Soup | C46: 1.89 | D46: < AVG | E46: 4.4966667 | F46: < MED | G46: 1.95
C47: AVG > | D47: =COUNTIF(D2:D46,"*>*") -> 14 | E47: MED > | F47: =COUNTIF(F2:F46,"*>*") -> 16
C48: AVG = | D48: =COUNTIF(D2:D46,"*=*") -> 5 | E48: MED = | F48: =COUNTIF(F2:F46,"*=*") -> 13
C49: AVG < | D49: =COUNTIF(D2:D46,"*<*") -> 26 | E49: MED < | F49: =COUNTIF(F2:F46,"*<*") -> 16

Sheet 8_products_KPI
A1: categories_unique | B1: products_unique | C1: active_products | D1: discontinued_products | E1: products_sold | F1: never_sold_products | G1: average_product_price | H1: average_units_per_product
A2: 16 | B2: 45 | C2: 45 | D2: 0 | E2: 2382 | F2: 21 | G2: 15.85 | H2: 52.93

Sheet 9_top_products
A1: rating_type | B1: product_name | C1: id | D1: category | E1: list_price | F1: revenue | G1: revenue_share_percent | H1: abc_category
A2: top_selling_product | B2: Northwind Traders Beer | C2: =INDEX('6_revenue_percent'!$B$2:$B$25,MATCH(B2,'6_revenue_percent'!$C$2:$C$25,0)) -> 34 | D2: =INDEX('6_revenue_percent'!$A$2:$A$25,MATCH(B2,'6_revenue_percent'!$C$2:$C$25,0)) -> Beverages | E2: =VLOOKUP(B2,'7_AVG_MED'!$B$2:$C$46,2,0) -> 14 | F2: =VLOOKUP(B2,'6_revenue_percent'!$C$2:$D$25,2,0) -> 6818 | G2: =VLOOKUP(B2,'10_ABC'!$B$2:$D$25,3,0) -> 0.1366 | H2: =VLOOKUP(B2,'10_ABC'!$B$2:$F$25,5,0) -> A
A3: top_revenue_product | B3: Northwind Traders Coffee | C3: =INDEX('6_revenue_percent'!$B$2:$B$25,MATCH(B3,'6_revenue_percent'!$C$2:$C$25,0)) -> 43 | D3: =INDEX('6_revenue_percent'!$A$2:$A$25,MATCH(B3,'6_revenue_percent'!$C$2:$C$25,0)) -> Beverages | E3: =VLOOKUP(B3,'7_AVG_MED'!$B$2:$C$46,2,0) -> 46 | F3: =VLOOKUP(B3,'6_revenue_percent'!$C$2:$D$25,2,0) -> 14950 | G3: =VLOOKUP(B3,'10_ABC'!$B$2:$D$25,3,0) -> 0.2995 | H3: =VLOOKUP(B3,'10_ABC'!$B$2:$F$25,5,0) -> A
A4: top_price_product | B4: Northwind Traders Marmalade | C4: =INDEX('6_revenue_percent'!$B$2:$B$25,MATCH(B4,'6_revenue_percent'!$C$2:$C$25,0)) -> 20 | D4: =INDEX('6_revenue_percent'!$A$2:$A$25,MATCH(B4,'6_revenue_percent'!$C$2:$C$25,0)) -> Jams, Preserves | E4: =VLOOKUP(B4,'7_AVG_MED'!$B$2:$C$46,2,0) -> 81 | F4: =VLOOKUP(B4,'6_revenue_percent'!$C$2:$D$25,2,0) -> 3240 | G4: =VLOOKUP(B4,'10_ABC'!$B$2:$D$25,3,0) -> 0.0649 | H4: =VLOOKUP(B4,'10_ABC'!$B$2:$F$25,5,0) -> A

Sheet 10_ABC
A1: id | B1: product_name | C1: revenue | D1: revenue_share_percent | E1: cumulative_share_percent | F1: abc_category | G1: category | H1: Количество по полю product_name | I1: Названия столбцов | M1: list_price
A2: 43 | B2: Northwind Traders Coffee | C2: 14950 | D2: 0.2995 | E2: 0.2995 | F2: A | G2: =INDEX('6_revenue_percent'!$A$2:$A$25,MATCH(B2,'6_revenue_percent'!$C$2:$C$25,0)) -> Beverages | H2: category | I2: A | J2: B | K2: C | L2: Общий итог | M2: =VLOOKUP(B2,'7_AVG_MED'!$B$2:$C$46,2,0) -> 46
A3: 34 | B3: Northwind Traders Beer | C3: 6818 | D3: 0.1366 | E3: 0.4361 | F3: A | G3: =INDEX('6_revenue_percent'!$A$2:$A$25,MATCH(B3,'6_revenue_percent'!$C$2:$C$25,0)) -> Beverages | H3: Baked Goods & Mixes | J3: 1 | K3: 1 | L3: 2 | M3: =VLOOKUP(B3,'7_AVG_MED'!$B$2:$C$46,2,0) -> 14
A4: 20 | B4: Northwind Traders Marmalade | C4: 3240 | D4: 0.0649 | E4: 0.501 | F4: A | G4: =INDEX('6_revenue_percent'!$A$2:$A$25,MATCH(B4,'6_revenue_percent'!$C$2:$C$25,0)) -> Jams, Preserves | H4: Beverages | I4: 2 | K4: 2 | L4: 4 | M4: =VLOOKUP(B4,'7_AVG_MED'!$B$2:$C$46,2,0) -> 81
A5: 72 | B5: Northwind Traders Mozzarella | C5: 3132 | D5: 0.0628 | E5: 0.5638 | F5: A | G5: =INDEX('6_revenue_percent'!$A$2:$A$25,MATCH(B5,'6_revenue_percent'!$C$2:$C$25,0)) -> Dairy products | H5: Candy | I5: 1 | L5: 1 | M5: =VLOOKUP(B5,'7_AVG_MED'!$B$2:$C$46,2,0) -> 34.8
A6: 41 | B6: Northwind Traders Clam Chowder | C6: 2798.5 | D6: 0.0561 | E6: 0.6199 | F6: A | G6: =INDEX('6_revenue_percent'!$A$2:$A$25,MATCH(B6,'6_revenue_percent'!$C$2:$C$25,0)) -> Soups | H6: Canned Fruit & Vegetables | J6: 1 | L6: 1 | M6: =VLOOKUP(B6,'7_AVG_MED'!$B$2:$C$46,2,0) -> 9.65
A7: 48 | B7: Northwind Traders Chocolate | C7: 2550 | D7: 0.0511 | E7: 0.6709 | F7: A | G7: =INDEX('6_revenue_percent'!$A$2:$A$25,MATCH(B7,'6_revenue_percent'!$C$2:$C$25,0)) -> Candy | H7: Canned Meat | J7: 1 | L7: 1 | M7: =VLOOKUP(B7,'7_AVG_MED'!$B$2:$C$46,2,0) -> 12.75
A8: 6 | B8: Northwind Traders Boysenberry Spread | C8: 2250 | D8: 0.0451 | E8: 0.716 | F8: A | G8: =INDEX('6_revenue_percent'!$A$2:$A$25,MATCH(B8,'6_revenue_percent'!$C$2:$C$25,0)) -> Jams, Preserves | H8: Condiments | J8: 1 | K8: 1 | L8: 2 | M8: =VLOOKUP(B8,'7_AVG_MED'!$B$2:$C$46,2,0) -> 25
A9: 51 | B9: Northwind Traders Dried Apples | C9: 2120 | D9: 0.0425 | E9: 0.7585 | F9: A | G9: =INDEX('6_revenue_percent'!$A$2:$A$25,MATCH(B9,'6_revenue_percent'!$C$2:$C$25,0)) -> Dried Fruit & Nuts | H9: Dairy products | I9: 1 | L9: 1 | M9: =VLOOKUP(B9,'7_AVG_MED'!$B$2:$C$46,2,0) -> 53
A10: 57 | B10: Northwind Traders Ravioli | C10: 1950 | D10: 0.0391 | E10: 0.7976 | F10: A | G10: =INDEX('6_revenue_percent'!$A$2:$A$25,MATCH(B10,'6_revenue_percent'!$C$2:$C$25,0)) -> Pasta | H10: Dried Fruit & Nuts | I10: 1 | J10: 1 | K10: 2 | L10: 4 | M10: =VLOOKUP(B10,'7_AVG_MED'!$B$2:$C$46,2,0) -> 19.5
A11: 8 | B11: Northwind Traders Curry Sauce | C11: 1800 | D11: 0.0361 | E11: 0.8336 | F11: B | G11: =INDEX('6_revenue_percent'!$A$2:$A$25,MATCH(B11,'6_revenue_percent'!$C$2:$C$25,0)) -> Sauces | H11: Grains | K11: 1 | L11: 1 | M11: =VLOOKUP(B11,'7_AVG_MED'!$B$2:$C$46,2,0) -> 40
A12: 17 | B12: Northwind Traders Fruit Cocktail | C12: 1560 | D12: 0.0313 | E12: 0.8649 | F12: B | G12: =INDEX('6_revenue_percent'!$A$2:$A$25,MATCH(B12,'6_revenue_percent'!$C$2:$C$25,0)) -> Canned Fruit & Vegetables | H12: Jams, Preserves | I12: 2 | L12: 2 | M12: =VLOOKUP(B12,'7_AVG_MED'!$B$2:$C$46,2,0) -> 39
A13: 40 | B13: Northwind Traders Crab Meat | C13: 1472 | D13: 0.0295 | E13: 0.8944 | F13: B | G13: =INDEX('6_revenue_percent'!$A$2:$A$25,MATCH(B13,'6_revenue_percent'!$C$2:$C$25,0)) -> Canned Meat | H13: Oil | K13: 1 | L13: 1 | M13: =VLOOKUP(B13,'7_AVG_MED'!$B$2:$C$46,2,0) -> 18.4
A14: 7 | B14: Northwind Traders Dried Pears | C14: 1200 | D14: 0.024 | E14: 0.9184 | F14: B | G14: =INDEX('6_revenue_percent'!$A$2:$A$25,MATCH(B14,'6_revenue_percent'!$C$2:$C$25,0)) -> Dried Fruit & Nuts | H14: Pasta | I14: 1 | K14: 1 | L14: 2 | M14: =VLOOKUP(B14,'7_AVG_MED'!$B$2:$C$46,2,0) -> 30
A15: 19 | B15: Northwind Traders Chocolate Biscuits Mix | C15: 690 | D15: 0.0138 | E15: 0.9322 | F15: B | G15: =INDEX('6_revenue_percent'!$A$2:$A$25,MATCH(B15,'6_revenue_percent'!$C$2:$C$25,0)) -> Baked Goods & Mixes | H15: Sauces | J15: 1 | L15: 1 | M15: =VLOOKUP(B15,'7_AVG_MED'!$B$2:$C$46,2,0) -> 9.2
A16: 4 | B16: Northwind Traders Cajun Seasoning | C16: 660 | D16: 0.0132 | E16: 0.9455 | F16: B | G16: =INDEX('6_revenue_percent'!$A$2:$A$25,MATCH(B16,'6_revenue_percent'!$C$2:$C$25,0)) -> Condiments | H16: Soups | I16: 1 | L16: 1 | M16: =VLOOKUP(B16,'7_AVG_MED'!$B$2:$C$46,2,0) -> 22
A17: 81 | B17: Northwind Traders Green Tea | C17: 598 | D17: 0.012 | E17: 0.9575 | F17: C | G17: =INDEX('6_revenue_percent'!$A$2:$A$25,MATCH(B17,'6_revenue_percent'!$C$2:$C$25,0)) -> Beverages | H17: Общий итог | I17: 9 | J17: 6 | K17: 9 | L17: 24 | M17: =VLOOKUP(B17,'7_AVG_MED'!$B$2:$C$46,2,0) -> 2.99
A18: 5 | B18: Northwind Traders Olive Oil | C18: 533.75 | D18: 0.0107 | E18: 0.9681 | F18: C | G18: =INDEX('6_revenue_percent'!$A$2:$A$25,MATCH(B18,'6_revenue_percent'!$C$2:$C$25,0)) -> Oil | M18: =VLOOKUP(B18,'7_AVG_MED'!$B$2:$C$46,2,0) -> 21.35
A19: 3 | B19: Northwind Traders Syrup | C19: 500 | D19: 0.01 | E19: 0.9782 | F19: C | G19: =INDEX('6_revenue_percent'!$A$2:$A$25,MATCH(B19,'6_revenue_percent'!$C$2:$C$25,0)) -> Condiments | H19: ABC | I19: revenue_abc | M19: =VLOOKUP(B19,'7_AVG_MED'!$B$2:$C$46,2,0) -> 10
A20: 52 | B20: Northwind Traders Long Grain Rice | C20: 280 | D20: 0.0056 | E20: 0.9838 | F20: C | G20: =INDEX('6_revenue_percent'!$A$2:$A$25,MATCH(B20,'6_revenue_percent'!$C$2:$C$25,0)) -> Grains | H20: A | I20: =SUMIF(_10_ABC[abc_category],H20,_10_ABC[revenue]) -> 39808.5 | M20: =VLOOKUP(B20,'7_AVG_MED'!$B$2:$C$46,2,0) -> 7
A21: 1 | B21: Northwind Traders Chai | C21: 270 | D21: 0.0054 | E21: 0.9892 | F21: C | G21: =INDEX('6_revenue_percent'!$A$2:$A$25,MATCH(B21,'6_revenue_percent'!$C$2:$C$25,0)) -> Beverages | H21: B | I21: =SUMIF(_10_ABC[abc_category],H21,_10_ABC[revenue]) -> 7382 | M21: =VLOOKUP(B21,'7_AVG_MED'!$B$2:$C$46,2,0) -> 18
A22: 21 | B22: Northwind Traders Scones | C22: 200 | D22: 0.004 | E22: 0.9972 | F22: C | G22: =INDEX('6_revenue_percent'!$A$2:$A$25,MATCH(B22,'6_revenue_percent'!$C$2:$C$25,0)) -> Baked Goods & Mixes | H22: C | I22: =SUMIF(_10_ABC[abc_category],H22,_10_ABC[revenue]) -> 2721.75 | M22: =VLOOKUP(B22,'7_AVG_MED'!$B$2:$C$46,2,0) -> 10
A23: 74 | B23: Northwind Traders Almonds | C23: 200 | D23: 0.004 | E23: 0.9972 | F23: C | G23: =INDEX('6_revenue_percent'!$A$2:$A$25,MATCH(B23,'6_revenue_percent'!$C$2:$C$25,0)) -> Dried Fruit & Nuts | M23: =VLOOKUP(B23,'7_AVG_MED'!$B$2:$C$46,2,0) -> 10
A24: 80 | B24: Northwind Traders Dried Plums | C24: 140 | D24: 0.0028 | E24: 1 | F24: C | G24: =INDEX('6_revenue_percent'!$A$2:$A$25,MATCH(B24,'6_revenue_percent'!$C$2:$C$25,0)) -> Dried Fruit & Nuts | M24: =VLOOKUP(B24,'7_AVG_MED'!$B$2:$C$46,2,0) -> 3.5
A25: 56 | B25: Northwind Traders Gnocchi | C25: 0 | D25: 0 | E25: 1 | F25: C | G25: =INDEX('6_revenue_percent'!$A$2:$A$25,MATCH(B25,'6_revenue_percent'!$C$2:$C$25,0)) -> Pasta | M25: =VLOOKUP(B25,'7_AVG_MED'!$B$2:$C$46,2,0) -> 38
